omnicli/__init__.py
omnicli/argparser.py
omnicli/errors.py
omnicli_sdk-0.1.0.dist-info/METADATA
omnicli_sdk-0.1.0.dist-info/WHEEL
omnicli_sdk-0.1.0.dist-info/licenses/LICENSE
omnicli_sdk-0.1.0.dist-info/RECORD
