Metadata-Version: 2.3
Name: omnicli-sdk
Version: 0.1.0
Summary: Omni Python SDK
Project-URL: Homepage, https://omnicli.dev
Project-URL: Documentation, https://omnicli.dev
Project-URL: Repository, https://github.com/omnicli/sdk-python.git
Project-URL: Issues, https://github.com/omnicli/sdk-python/issues
Project-URL: Changelog, https://github.com/omnicli/sdk-python/commits/main/
Author-email: Raphaël Beamonte <raphael.beamonte@gmail.com>
License: MIT License
Keywords: omni,omnicli,sdk
Classifier: Development Status :: 4 - Beta
Classifier: Intended Audience :: Developers
Classifier: License :: OSI Approved :: MIT License
Classifier: Programming Language :: Python :: 3
Requires-Python: >=3.8
